Verilog/CPU-BOARD-3202/circuit/BIF_DPATH_PPNLBD_14.v
/**************************************************************************
** ND120 CPU, MM&M                                                       **
** BIF/DPATH/PPNLBD                                                      **
** BIF PPN TO LBD                                                        **
** SHEET 14  of 50                                                       **
**                                                                       **
** Last reviewed: 09-NOV-2024                                            **
** Ronny Hansen                                                          **
***************************************************************************/

module BIF_DPATH_PPNLBD_14 (
    input [13:0] PPN_23_10,
    input [ 9:0] CA_9_0,

    input EADR_n,
    input ECREQ,

    output [23:0] LBD_23_0_OUT
);

  reg [23:0] Q_reg;  // Internal register

  // Latch data on rising edge of CK
  always @(posedge ECREQ) begin
    Q_reg <= {PPN_23_10[13:0], CA_9_0[9:0]};
  end

  assign LBD_23_0_OUT = EADR_n ? 24'b0 : Q_reg;
endmodule

Verilog/CPU-BOARD-3202/circuit/BIF_DPATH_PPNLBD_14/sim/waveform.vcd
$version Generated by VerilatedVcd $end
$timescale 1ps $end
 $scope module TOP $end
  $var wire 14 # PPN_23_10 [13:0] $end
  $var wire 10 $ CA_9_0 [9:0] $end
  $var wire 1 % EADR_n $end
  $var wire 1 & ECREQ $end
  $var wire 24 ' LBD_23_0_OUT [23:0] $end
  $scope module BIF_DPATH_PPNLBD_14 $end
   $var wire 14 # PPN_23_10 [13:0] $end
   $var wire 10 $ CA_9_0 [9:0] $end
   $var wire 1 % EADR_n $end
   $var wire 1 & ECREQ $end
   $var wire 24 ' LBD_23_0_OUT [23:0] $end
   $var wire 24 ( Q_reg [23:0] $end
  $upscope $end
 $upscope $end
$enddefinitions $end


#0
b11111100000000 #
b0000000000 $
1%
1&
b000000000000000000000000 '
b000000000000000000000000 (
#5
0&
#10
b11111100000001 #
b0000000001 $
1&
b111111000000010000000001 (
#15
0&
#20
b11111100000010 #
b0000000010 $
1&
b111111000000100000000010 (
#25
0&
#30
b11111100000011 #
b0000000011 $
0%
1&
b111111000000110000000011 '
b111111000000110000000011 (
#35
0&
#40
b11111100000100 #
b0000000100 $
1&
b111111000001000000000100 '
b111111000001000000000100 (
#45
0&
#50
b11111100000101 #
b0000000101 $
1&
b111111000001010000000101 '
b111111000001010000000101 (
#55
0&
#60
b11111100000110 #
b0000000110 $
1&
b111111000001100000000110 '
b111111000001100000000110 (
#65
0&
#70
b11111100000111 #
b0000000111 $
1&
b111111000001110000000111 '
b111111000001110000000111 (
#75
0&
#80
b11111100001000 #
b0000001000 $
1%
1&
b000000000000000000000000 '
b111111000010000000001000 (
#85
0&
#90
b11111100001001 #
b0000001001 $
1&
b111111000010010000001001 (
#95
0&
#100
b11111100001010 #
b0000001010 $
1&
b111111000010100000001010 (
#105
0&
#110
b11111100001011 #
b0000001011 $
1&
b111111000010110000001011 (
#115
0&
#120
b11111100001100 #
b0000001100 $
1&
b111111000011000000001100 (
#125
0&
#130
b11111100001101 #
b0000001101 $
1&
b111111000011010000001101 (
#135
0&
#140
b11111100001110 #
b0000001110 $
1&
b111111000011100000001110 (
#145
0&
#150
b11111100001111 #
b0000001111 $
1&
b111111000011110000001111 (
#155
0&
#160
b11111100010000 #
b0000010000 $
1&
b111111000100000000010000 (
#165
0&
#170
b11111100010001 #
b0000010001 $
1&
b111111000100010000010001 (
#175
0&
#180
b11111100010010 #
b0000010010 $
1&
b111111000100100000010010 (
#185
0&
#190
b11111100010011 #
b0000010011 $
1&
b111111000100110000010011 (
#195
0&
#200
b11111100010100 #
b0000010100 $
1&
b111111000101000000010100 (
#205
0&
#210
b11111100010101 #
b0000010101 $
1&
b111111000101010000010101 (
#215
0&
#220
b11111100010110 #
b0000010110 $
1&
b111111000101100000010110 (
#225
0&
#230
b11111100010111 #
b0000010111 $
1&
b111111000101110000010111 (
#235
0&
#240
b11111100011000 #
b0000011000 $
1&
b111111000110000000011000 (
#245
0&
#250
b11111100011001 #
b0000011001 $
1&
b111111000110010000011001 (
#255
0&
#260
b11111100011010 #
b0000011010 $
1&
b111111000110100000011010 (
#265
0&
#270
b11111100011011 #
b0000011011 $
1&
b111111000110110000011011 (
#275
0&
#280
b11111100011100 #
b0000011100 $
1&
b111111000111000000011100 (
#285
0&
#290
b11111100011101 #
b0000011101 $
1&
b111111000111010000011101 (
#295
0&
