Verilog/Shared/support/FIFO_8BIT.v
module FIFO_8BIT #(
    parameter DEPTH = 13  // Depth of the FIFO (maximum 16)
) (
    input rst,                // Asynchronous reset
    input wr_en,              // Write enable
    input rd_en,              // Read enable
    input [7:0] data_in,      // Data input
    output reg [7:0] data_out,// Data output
    output full,              // FIFO full flag
    output empty              // FIFO empty flag
);

    // Calculate address width based on depth
    localparam ADDR_WIDTH = $clog2(DEPTH + 1);

    reg [7:0] mem [0:DEPTH-1];  // Memory array
    reg [ADDR_WIDTH-1:0] wr_ptr; // Write pointer
    reg [ADDR_WIDTH-1:0] rd_ptr; // Read pointer
    reg [ADDR_WIDTH:0] fifo_count; // Counter for number of elements in the FIFO

    // Write operation
    always @(*) begin
        if (wr_en && !full) begin
            mem[wr_ptr] = data_in;
            wr_ptr = (wr_ptr == (DEPTH - 1)) ? 0 : wr_ptr + 1;
        end
    end

    // Read operation
    always @(*) begin
        if (rd_en && !empty) begin
            data_out = mem[rd_ptr];
            rd_ptr = (rd_ptr == (DEPTH - 1)) ? 0 : rd_ptr + 1;
        end
    end

    // FIFO count management
    always @(*) begin
        if (rst) begin
            fifo_count = 0;
            wr_ptr = 0;
            rd_ptr = 0;
            data_out = 8'b0;
        end else begin
            if (wr_en && !rd_en && !full) begin
                fifo_count = fifo_count + 1;
            end else if (!wr_en && rd_en && !empty) begin
                fifo_count = fifo_count - 1;
            end
        end
    end

    // Full and empty flags
    assign full = (fifo_count == DEPTH);
    assign empty = (fifo_count == 0);

endmodule

Verilog/Shared/support/FIFO_8BIT_TB/FIFO_tb.v
module FIFO_testbench;

    // Parameters
    parameter DEPTH = 13;

    // Signals
    reg rst;
    reg wr_en;
    reg rd_en;
    reg [7:0] data_in;
    wire [7:0] data_out;
    wire full;
    wire empty;

    // Instantiate the FIFO module
    FIFO_8BIT #(
        .DEPTH(DEPTH)
    ) fifo_inst (
        .rst(rst),
        .wr_en(wr_en),
        .rd_en(rd_en),
        .data_in(data_in),
        .data_out(data_out),
        .full(full),
        .empty(empty)
    );

    // Test procedure
    initial begin
        $dumpfile("fifo_tb.vcd");
        $dumpvars(0, FIFO_testbench);

        // Initialize signals
        rst = 1;
        wr_en = 0;
        rd_en = 0;
        data_in = 8'b0;

        // Apply reset
        #10 rst = 0;

        // Write some data into the FIFO
        #10 data_in = 8'hA5; wr_en = 1;
        #10 wr_en = 0;

        #10 data_in = 8'h5A; wr_en = 1;
        #10 wr_en = 0;

        // Reset the FIFO
        #10 rst = 1;
        // Clear reset signal
        #10 rst = 0;

        // Write some more data into the FIFO
        #10 data_in = 8'hB5; wr_en = 1;
        #10 wr_en = 0;

        #10 data_in = 8'h6B; wr_en = 1;
        #10 wr_en = 0;


        // Read the data back from the FIFO
        #10 rd_en = 1;
        #10 rd_en = 0;

        #10 rd_en = 1;
        #10 rd_en = 0;

        // Check the full and empty flags
        #10 $display("Full: %b, Empty: %b", full, empty);

        // Overflow the FIFO
         // Write some more data into the FIFO
        #10 data_in = 8'hF0; wr_en = 1;
        #10 wr_en = 0;

        #10 data_in = 8'hF1; wr_en = 1;
        #10 wr_en = 0;

        #10 data_in = 8'hF2; wr_en = 1;
        #10 wr_en = 0;

        #10 data_in = 8'hF3; wr_en = 1;
        #10 wr_en = 0;

        #10 data_in = 8'hF4; wr_en = 1;
        #10 wr_en = 0;

        #10 data_in = 8'hF5; wr_en = 1;
        #10 wr_en = 0;

        #10 data_in = 8'hF6; wr_en = 1;
        #10 wr_en = 0;

        #10 data_in = 8'hF7; wr_en = 1;
        #10 wr_en = 0;

        #10 data_in = 8'hF8; wr_en = 1;
        #10 wr_en = 0;

        #10 data_in = 8'hF9; wr_en = 1;
        #10 wr_en = 0;

        #10 data_in = 8'hFA; wr_en = 1;
        #10 wr_en = 0;

        #10 data_in = 8'hFB; wr_en = 1;
        #10 wr_en = 0;

        #10 data_in = 8'hFC; wr_en = 1;
        #10 wr_en = 0;

        #10 data_in = 8'hFD; wr_en = 1;
        #10 wr_en = 0;

        // Check the full and empty flags
        #10 $display("Full: %b, Empty: %b", full, empty);


        
        // Read the data back from the FIFO
        #10 rd_en = 1;
        #10 rd_en = 0;

        #10 rd_en = 1;
        #10 rd_en = 0;

        #10 rd_en = 1;
        #10 rd_en = 0;

        #10 rd_en = 1;
        #10 rd_en = 0;


        #10 rd_en = 1;
        #10 rd_en = 0;

        #10 rd_en = 1;
        #10 rd_en = 0;


        #10 rd_en = 1;
        #10 rd_en = 0;

        #10 rd_en = 1;
        #10 rd_en = 0;


        #10 rd_en = 1;
        #10 rd_en = 0;

        #10 rd_en = 1;
        #10 rd_en = 0;


        #10 rd_en = 1;
        #10 rd_en = 0;

        #10 rd_en = 1;
        #10 rd_en = 0;


        #10 rd_en = 1;
        #10 rd_en = 0;

        #10 rd_en = 1;
        #10 rd_en = 0;


        #10 rd_en = 1;
        #10 rd_en = 0;

        #10 rd_en = 1;
        #10 rd_en = 0;


        #10 rd_en = 1;
        #10 rd_en = 0;

        #10 rd_en = 1;
        #10 rd_en = 0;


        #10 rd_en = 1;
        #10 rd_en = 0;

        #10 rd_en = 1;
        #10 rd_en = 0;

        // Check the full and empty flags
        #10 $display("Full: %b, Empty: %b", full, empty);


        // End of test
        #10 $finish;
    end

endmodule

Verilog/Shared/support/FIFO_8BIT_TB/fifo_tb.vcd
$date
	Mon May 20 13:48:17 2024
$end
$version
	Icarus Verilog
$end
$timescale
	1s
$end
$scope module FIFO_testbench $end
$var wire 1 ! full $end
$var wire 1 " empty $end
$var wire 8 # data_out [7:0] $end
$var reg 8 $ data_in [7:0] $end
$var reg 1 % rd_en $end
$var reg 1 & rst $end
$var reg 1 ' wr_en $end
$scope module fifo_inst $end
$var wire 8 ( data_in [7:0] $end
$var wire 1 % rd_en $end
$var wire 1 & rst $end
$var wire 1 ' wr_en $end
$var reg 8 ) data_out [7:0] $end
$var reg 1 " empty $end
$var reg 5 * fifo_count [4:0] $end
$var reg 1 ! full $end
$var reg 4 + rd_ptr [3:0] $end
$var reg 4 , wr_ptr [3:0] $end
$upscope $end
$upscope $end
$enddefinitions $end
#0
$dumpvars
b0 ,
b0 +
b0 *
b0 )
b0 (
0'
1&
0%
b0 $
b0 #
1"
0!
$end
#10
0&
#20
0"
b1 *
b1 ,
1'
b10100101 $
b10100101 (
#30
0'
#40
b10 *
b10 ,
1'
b1011010 $
b1011010 (
#50
0'
#60
1"
b0 *
b0 ,
1&
#70
0&
#80
0"
b1 *
b1 ,
1'
b10110101 $
b10110101 (
#90
0'
#100
b10 *
b10 ,
1'
b1101011 $
b1101011 (
#110
0'
#120
b1 *
b10110101 #
b10110101 )
b1 +
1%
#130
0%
#140
1"
b0 *
b1101011 #
b1101011 )
b10 +
1%
#150
0%
#170
0"
b1 *
b11 ,
1'
b11110000 $
b11110000 (
#180
0'
#190
b10 *
b100 ,
1'
b11110001 $
b11110001 (
#200
0'
#210
b11 *
b101 ,
1'
b11110010 $
b11110010 (
#220
0'
#230
b100 *
b110 ,
1'
b11110011 $
b11110011 (
#240
0'
#250
b101 *
b111 ,
1'
b11110100 $
b11110100 (
#260
0'
#270
b110 *
b1000 ,
1'
b11110101 $
b11110101 (
#280
0'
#290
b111 *
b1001 ,
1'
b11110110 $
b11110110 (
#300
0'
#310
b1000 *
b1010 ,
1'
b11110111 $
b11110111 (
#320
0'
#330
b1001 *
b1011 ,
1'
b11111000 $
b11111000 (
#340
0'
#350
b1010 *
b1100 ,
1'
b11111001 $
b11111001 (
#360
0'
#370
b1011 *
b0 ,
1'
b11111010 $
b11111010 (
#380
0'
#390
b1100 *
b1 ,
1'
b11111011 $
b11111011 (
#400
0'
#410
1!
b1101 *
b10 ,
1'
b11111100 $
b11111100 (
#420
0'
#430
1'
b11111101 $
b11111101 (
#440
0'
#460
0!
b1100 *
b11110000 #
b11110000 )
b11 +
1%
#470
0%
#480
b1011 *
b11110001 #
b11110001 )
b100 +
1%
#490
0%
#500
b1010 *
b11110010 #
b11110010 )
b101 +
1%
#510
0%
#520
b1001 *
b11110011 #
b11110011 )
b110 +
1%
#530
0%
#540
b1000 *
b11110100 #
b11110100 )
b111 +
1%
#550
0%
#560
b111 *
b11110101 #
b11110101 )
b1000 +
1%
#570
0%
#580
b110 *
b11110110 #
b11110110 )
b1001 +
1%
#590
0%
#600
b101 *
b11110111 #
b11110111 )
b1010 +
1%
#610
0%
#620
b100 *
b11111000 #
b11111000 )
b1011 +
1%
#630
0%
#640
b11 *
b11111001 #
b11111001 )
b1100 +
1%
#650
0%
#660
b10 *
b11111010 #
b11111010 )
b0 +
1%
#670
0%
#680
b1 *
b11111011 #
b11111011 )
b1 +
1%
#690
0%
#700
1"
b0 *
b11111100 #
b11111100 )
b10 +
1%
#710
0%
#720
1%
#730
0%
#740
1%
#750
0%
#760
1%
#770
0%
#780
1%
#790
0%
#800
1%
#810
0%
#820
1%
#830
0%
#840
1%
#850
0%
