Verilog/DECODE-GateArray/DGA/circuit/F714.v
/**************************************************************************
** ND120 DGA (Decode Gate Array)                                         **
** DECODE/DGA                                                            **
**                                                                       **
** NEC F714 - T Flip-Flop with R, S                                      **
**                                                                       **
** Last reviewed: 20-MAY-2024                                            **
** Ronny Hansen                                                          **
***************************************************************************/

module F714
( 
   input H01_T,   // Toggle
   input H02_R,   // Reset
   input H03_S,   // Set

   output N01_Q,
   output N02_QB
);


reg regQ;
reg reqQ_n;

// Wires
wire s_t;
wire s_r;
wire s_s;


// Assign inputs
assign s_t     = H01_T;
assign s_r     = H02_R;
assign s_s     = H03_S;


// Assign outputs
assign N01_Q   = regQ;
assign N02_QB  = reqQ_n;


always @(posedge s_t or posedge s_r or posedge s_s) begin      
   if (s_r | s_s)  begin
      if (!s_s & s_r) begin // reset
         regQ   <= 1'b0;
         reqQ_n <= 1'b1;
      end else if (s_s & !s_r) begin // set 
         regQ   <= 1'b1;
         reqQ_n <= 1'b0;
      end else begin /* s_rb & s_sb */  
         regQ   <= 1'b1;
         reqQ_n <= 1'b1;
      end
   end else begin
      if (s_t) begin

         reqQ_n <=  regQ;
         regQ   <= ~regQ;
         
      end
   end
end

endmodule


/* 

TRUTH TABLE
===========

| T       | R | S | Q | QB |
|---------|---|---|---|----|
| posedge | 0 | 0 | Invert | 
| negedge | 0 | 0 |  Hold  |
|   X     | 1 | 0 | 0 | 1  |
|   X     | 0 | 1 | 1 | 0  |
|   X     | 1 | 1 | 1 | 1  |  <= prohibition

X=irrelevant

*/

Verilog/DECODE-GateArray/DGA/circuit/F714_TEST/F714_tb.v
`timescale 1ns/1ns

module F714_testbench;

  // Inputs
  reg H01_T;
  reg H02_R;
  reg H03_S;

  // Outputs
  wire N01_Q;
  wire N02_QB;

  // Instantiate the UUT (Unit Under Test)
  F714 uut (
    .H01_T(H01_T),
    .H02_R(H02_R),
    .H03_S(H03_S),
    .N01_Q(N01_Q),
    .N02_QB(N02_QB)
  );

  initial begin
    $dumpfile("F714_tb.vcd");
    $dumpvars(0, F714_testbench);


    // Initialize inputs
    H01_T = 0;
    H02_R = 0;    
    H03_S = 0;

    // Apply reset
    #10 H02_R = 1;

    // Apply different test cases
    // Test reset condition
    #10;
    H02_R = 1;
    #10;
    H02_R = 0;

    // Test set condition
    #10;
    H03_S = 1;
    #10;
    H03_S = 0;

    // Test toggle condition
    #10;
    H02_R = 0;
    H03_S = 0;
    H01_T = 1;
    #20;
    H01_T = 0;

    // Test toggle condition #2
    #10;
    H02_R = 0;
    H03_S = 0;
    H01_T = 1;
    #20;
    H01_T = 0;


    // Test prohibition condition
    #10;
    H02_R = 1;
    H03_S = 1;
    #10;
    H02_R = 0;
    H03_S = 0;

    // Test moving from prohibition to toggle
    #10;
    H02_R = 1;
    H03_S = 1;
    #10;
    H02_R = 0;
    H03_S = 0;
    #20;
    
    // Test toggle condition #3
    #10;
    H02_R = 0;
    H03_S = 0;
    H01_T = 1;
    #20;
    H01_T = 0;


    // Test toggle condition #4
    #10;
    H02_R = 0;
    H03_S = 0;
    H01_T = 1;
    #20;
    H01_T = 0;

    // End of test
    #10 $finish;
  end

  initial begin
    $monitor("At time %t, T = %b, R = %b, S = %b, Q = %b, QB = %b",
             $time, H01_T, H02_R, H03_S, N01_Q, N02_QB);
  end

endmodule

Verilog/DECODE-GateArray/DGA/circuit/F714_TEST/F714_tb.vcd
$date
	Sat Jun  1 21:35:19 2024
$end
$version
	Icarus Verilog
$end
$timescale
	1ns
$end
$scope module F714_testbench $end
$var wire 1 ! N02_QB $end
$var wire 1 " N01_Q $end
$var reg 1 # H01_T $end
$var reg 1 $ H02_R $end
$var reg 1 % H03_S $end
$scope module uut $end
$var wire 1 # H01_T $end
$var wire 1 $ H02_R $end
$var wire 1 % H03_S $end
$var wire 1 " N01_Q $end
$var wire 1 ! N02_QB $end
$var wire 1 & s_r $end
$var wire 1 ' s_s $end
$var wire 1 ( s_t $end
$var reg 1 ) regQ $end
$var reg 1 * reqQ_n $end
$upscope $end
$upscope $end
$enddefinitions $end
#0
$dumpvars
x*
x)
0(
0'
0&
0%
0$
0#
x"
x!
$end
#10
1!
1*
0"
0)
1&
1$
#30
0&
0$
#40
0!
0*
1"
1)
1'
1%
#50
0'
0%
#60
0"
0)
1!
1*
1(
1#
#80
0(
0#
#90
1"
1)
0!
0*
1(
1#
#110
0(
0#
#120
1!
1*
1'
1%
1&
1$
#130
0'
0%
0&
0$
#140
1'
1%
1&
1$
#150
0'
0%
0&
0$
#180
0"
0)
1(
1#
#200
0(
0#
#210
1"
1)
0!
0*
1(
1#
#230
0(
0#
